main/commutator.v
`timescale 1ns/1ns

module multiplexer_8_to_1(d,control,out);
    input [2:0]control;
    input [7:0]d;
    output reg out;
    always @ (d[0] or d[1] or d[2] or d[3] or d[4] or d[5] or d[6] or d[7] or control[0] or control[1]) begin
       case(control) 
       3'b000 : out <= d[0];
       3'b100 : out <= d[1];
       3'b010 : out <= d[2];
       3'b110 : out <= d[3];
       3'b001 : out <= d[4];
       3'b101 : out <= d[5];
       3'b011 : out <= d[6];
       3'b111 : out <= d[7];
       default : out <= 0;
       endcase
    end
endmodule

module mx_reg(d,control,out);
    input [7:0] d;
    input [2:0][2:0] control;
    output [2:0] out;
    multiplexer_8_to_1 dd0(.d(d), .control(control[0]), .out(out[0]));
    multiplexer_8_to_1 dd1(.d(d), .control(control[1]), .out(out[1]));
    multiplexer_8_to_1 dd2(.d(d), .control(control[2]), .out(out[2]));
endmodule

module d_trigger(d,clk,q,qbar);
    output reg q;
    output qbar;
    input d, clk;
    assign qbar = ~q;
    always @ (d or clk) begin
        if (clk)
       #1 q = d;
    end
endmodule

module mem_reg(control,clk,out);
    input  clk;
    input [2:0] control;
    output [2:0] out;
    d_trigger dd0(.d(control[0]), .clk(clk), .q(out[0]), .qbar());
    d_trigger dd1(.d(control[1]), .clk(clk), .q(out[1]), .qbar());
    d_trigger dd2(.d(control[2]), .clk(clk), .q(out[2]), .qbar());
endmodule

module mem3_reg(control,clk,out);
    input  [2:0]clk;
    input [2:0] control;
    output [2:0][2:0] out;
    mem_reg dd0(.control(control), .clk(clk[0]), .out(out[0]));
    mem_reg dd1(.control(control), .clk(clk[1]), .out(out[1]));
    mem_reg dd2(.control(control), .clk(clk[2]), .out(out[2]));
endmodule

module commutator(inputs,control,clk,outputs);
    input  [2:0]clk;
    input [2:0] control;
    input [7:0] inputs;
    output [2:0] outputs;
    wire [2:0][2:0] mem_out;
    mem3_reg dd0(.control(control),.clk(clk),.out(mem_out));
    mx_reg dd1(.d(inputs),.control(mem_out),.out(outputs));
endmodule

module top(inputs_i,control_i,clk_i,outputs_o);
    input  [2:0]clk_i;
    input [2:0] control_i;
    input [7:0] inputs_i;
    output [2:0][2:0] outputs_o;

    wire [2:0] clk;
    wire [2:0] control;
    wire [7:0] inputs;
    wire [2:0][2:0] outputs;
    wire vddc, vddo;
    wire vssc, vsso;

    commutator dd0(.inputs(inputs),.control(control),.clk(clk),.outputs(outputs));

    PADDI pad_clk(.A(clk_i), .Y(clk), .VDDIOR(vddo), .VSSIOR(vsso));
    PADDI pad_control(.A(control_i), .Y(control), .VDDIOR(vddo), .VSSIOR(vsso));
    PADDI pad_inputs(.A(inputs_i), .Y(inputs), .VDDIOR(vddo), .VSSIOR(vsso));
    PADDO pad_outputs(.A(outputs_i), .Y(outputs), .VDDIOR(vddo), .VSSIOR(vsso));

    PADVDD pad_vdd1(.VDD(vddc), .VDDIOR(vddo), .VSSIOR(vsso));
    PADVDD pad_vdd2(.VDD(vddc), .VDDIOR(vddo), .VSSIOR(vsso));
    PADVDD pad_vss1(.VSS(vssc), .VDDIOR(vddo), .VSSIOR(vsso));
    PADVDD pad_vss2(.VSS(vssc), .VDDIOR(vddo), .VSSIOR(vsso));

    PADVDDIOR pad_vddior(.VDDIOR(vddo), .VSSIOR(vsso));
    PADVSSIOR pad_vssior(.VDDIOR(vddo), .VSSIOR(vsso));
endmodule

main/commutator_test.v
`include "commutator.v"
`timescale 1ns/1ns

module commutator_test;
    reg [2:0] control;
    reg [2:0]clk;
    reg [7:0]inputs;
    wire [2:0]outputs;
    initial begin
        clk <= 3'b000;
        control <= 3'b000;
        inputs <= 8'b00000000;
    end
   commutator dd0(.inputs(inputs),.control(control),.clk(clk),.outputs(outputs));

    always #50 clk[0] = ~clk[0];  
    always #35 clk[1] = ~clk[1];
    always #43 clk[2] = ~clk[2];

    always #30 control[0] = ~control[0];
    always #27 control[1] = ~control[1];
    always #25 control[2] = ~control[2];

    always #12 inputs[0] = ~inputs[0];
    always #11 inputs[1] = ~inputs[1];
    always #10 inputs[2] = ~inputs[2];
    always #9 inputs[3] = ~inputs[3];
    always #8 inputs[4] = ~inputs[4];
    always #7 inputs[5] = ~inputs[5];
    always #4 inputs[6] = ~inputs[6];
    always #2 inputs[7] = ~inputs[7];
    initial begin
        $dumpfile("commutator_test.vcd");
        $dumpvars;
        $display("test complete");
        #400;
        $finish;
    end
endmodule

main/commutator_test.vcd
$date
	Mon May 23 12:18:25 2022
$end
$version
	Icarus Verilog
$end
$timescale
	1ns
$end
$scope module commutator_test $end
$var wire 3 ! outputs [2:0] $end
$var reg 3 " clk [2:0] $end
$var reg 3 # control [2:0] $end
$var reg 8 $ inputs [7:0] $end
$scope module dd0 $end
$var wire 3 % clk [2:0] $end
$var wire 3 & control [2:0] $end
$var wire 8 ' inputs [7:0] $end
$var wire 3 ( outputs [2:0] $end
$var wire 9 ) mem_out [8:0] $end
$scope module dd0 $end
$var wire 3 * clk [2:0] $end
$var wire 3 + control [2:0] $end
$var wire 9 , out [8:0] $end
$scope module dd0 $end
$var wire 1 - clk $end
$var wire 3 . control [2:0] $end
$var wire 3 / out [2:0] $end
$scope module dd0 $end
$var wire 1 - clk $end
$var wire 1 0 d $end
$var wire 1 1 qbar $end
$var reg 1 2 q $end
$upscope $end
$scope module dd1 $end
$var wire 1 - clk $end
$var wire 1 3 d $end
$var wire 1 4 qbar $end
$var reg 1 5 q $end
$upscope $end
$scope module dd2 $end
$var wire 1 - clk $end
$var wire 1 6 d $end
$var wire 1 7 qbar $end
$var reg 1 8 q $end
$upscope $end
$upscope $end
$scope module dd1 $end
$var wire 1 9 clk $end
$var wire 3 : control [2:0] $end
$var wire 3 ; out [2:0] $end
$scope module dd0 $end
$var wire 1 9 clk $end
$var wire 1 < d $end
$var wire 1 = qbar $end
$var reg 1 > q $end
$upscope $end
$scope module dd1 $end
$var wire 1 9 clk $end
$var wire 1 ? d $end
$var wire 1 @ qbar $end
$var reg 1 A q $end
$upscope $end
$scope module dd2 $end
$var wire 1 9 clk $end
$var wire 1 B d $end
$var wire 1 C qbar $end
$var reg 1 D q $end
$upscope $end
$upscope $end
$scope module dd2 $end
$var wire 1 E clk $end
$var wire 3 F control [2:0] $end
$var wire 3 G out [2:0] $end
$scope module dd0 $end
$var wire 1 E clk $end
$var wire 1 H d $end
$var wire 1 I qbar $end
$var reg 1 J q $end
$upscope $end
$scope module dd1 $end
$var wire 1 E clk $end
$var wire 1 K d $end
$var wire 1 L qbar $end
$var reg 1 M q $end
$upscope $end
$scope module dd2 $end
$var wire 1 E clk $end
$var wire 1 N d $end
$var wire 1 O qbar $end
$var reg 1 P q $end
$upscope $end
$upscope $end
$upscope $end
$scope module dd1 $end
$var wire 9 Q control [8:0] $end
$var wire 8 R d [7:0] $end
$var wire 3 S out [2:0] $end
$scope module dd0 $end
$var wire 3 T control [2:0] $end
$var wire 8 U d [7:0] $end
$var reg 1 V out $end
$upscope $end
$scope module dd1 $end
$var wire 3 W control [2:0] $end
$var wire 8 X d [7:0] $end
$var reg 1 Y out $end
$upscope $end
$scope module dd2 $end
$var wire 3 Z control [2:0] $end
$var wire 8 [ d [7:0] $end
$var reg 1 \ out $end
$upscope $end
$upscope $end
$upscope $end
$upscope $end
$enddefinitions $end
#0
$dumpvars
0\
b0 [
bx Z
0Y
b0 X
bx W
0V
b0 U
bx T
b0 S
b0 R
bx Q
xP
xO
0N
xM
xL
0K
xJ
xI
0H
bx G
b0 F
0E
xD
xC
0B
xA
x@
0?
x>
x=
0<
bx ;
b0 :
09
x8
x7
06
x5
x4
03
x2
x1
00
bx /
b0 .
0-
bx ,
b0 +
b0 *
bx )
b0 (
b0 '
b0 &
b0 %
b0 $
b0 #
b0 "
b0 !
$end
#2
b10000000 $
b10000000 '
b10000000 R
b10000000 U
b10000000 X
b10000000 [
#4
b1000000 $
b1000000 '
b1000000 R
b1000000 U
b1000000 X
b1000000 [
#6
b11000000 $
b11000000 '
b11000000 R
b11000000 U
b11000000 X
b11000000 [
#7
b11100000 $
b11100000 '
b11100000 R
b11100000 U
b11100000 X
b11100000 [
#8
b110000 $
b110000 '
b110000 R
b110000 U
b110000 X
b110000 [
#9
b111000 $
b111000 '
b111000 R
b111000 U
b111000 X
b111000 [
#10
b10111100 $
b10111100 '
b10111100 R
b10111100 U
b10111100 X
b10111100 [
#11
b10111110 $
b10111110 '
b10111110 R
b10111110 U
b10111110 X
b10111110 [
#12
b1111111 $
b1111111 '
b1111111 R
b1111111 U
b1111111 X
b1111111 [
#14
b11011111 $
b11011111 '
b11011111 R
b11011111 U
b11011111 X
b11011111 [
#16
b1111 $
b1111 '
b1111 R
b1111 U
b1111 X
b1111 [
#18
b10000111 $
b10000111 '
b10000111 R
b10000111 U
b10000111 X
b10000111 [
#20
b1000011 $
b1000011 '
b1000011 R
b1000011 U
b1000011 X
b1000011 [
#21
b1100011 $
b1100011 '
b1100011 R
b1100011 U
b1100011 X
b1100011 [
#22
b11100001 $
b11100001 '
b11100001 R
b11100001 U
b11100001 X
b11100001 [
#24
b110000 $
b110000 '
b110000 R
b110000 U
b110000 X
b110000 [
#25
16
1B
1N
b100 #
b100 &
b100 +
b100 .
b100 :
b100 F
#26
b10110000 $
b10110000 '
b10110000 R
b10110000 U
b10110000 X
b10110000 [
#27
13
1?
1K
b10111000 $
b10111000 '
b10111000 R
b10111000 U
b10111000 X
b10111000 [
b110 #
b110 &
b110 +
b110 .
b110 :
b110 F
#28
b1011000 $
b1011000 '
b1011000 R
b1011000 U
b1011000 X
b1011000 [
#30
10
1<
1H
b11011100 $
b11011100 '
b11011100 R
b11011100 U
b11011100 X
b11011100 [
b111 #
b111 &
b111 +
b111 .
b111 :
b111 F
#32
b1100 $
b1100 '
b1100 R
b1100 U
b1100 X
b1100 [
#33
b1110 $
b1110 '
b1110 R
b1110 U
b1110 X
b1110 [
#34
b10001110 $
b10001110 '
b10001110 R
b10001110 U
b10001110 X
b10001110 [
#35
19
b10101110 $
b10101110 '
b10101110 R
b10101110 U
b10101110 X
b10101110 [
b10 "
b10 %
b10 *
#36
0=
0@
0C
b111 W
1>
1A
bx111xxx )
bx111xxx ,
bx111xxx Q
b111 ;
1D
b1100111 $
b1100111 '
b1100111 R
b1100111 U
b1100111 X
b1100111 [
#38
b10 !
b10 (
b10 S
1Y
b11100111 $
b11100111 '
b11100111 R
b11100111 U
b11100111 X
b11100111 [
#40
b0 !
b0 (
b0 S
0Y
b110011 $
b110011 '
b110011 R
b110011 U
b110011 X
b110011 [
#42
b10 !
b10 (
b10 S
1Y
b10010011 $
b10010011 '
b10010011 R
b10010011 U
b10010011 X
b10010011 [
#43
1E
b110 "
b110 %
b110 *
#44
b0 !
b0 (
b0 S
0Y
0I
0L
0O
b111 Z
1J
1M
b111111xxx )
b111111xxx ,
b111111xxx Q
b111 G
1P
b1010001 $
b1010001 '
b1010001 R
b1010001 U
b1010001 X
b1010001 [
#45
b1011001 $
b1011001 '
b1011001 R
b1011001 U
b1011001 X
b1011001 [
#46
1Y
b110 !
b110 (
b110 S
1\
b11011001 $
b11011001 '
b11011001 R
b11011001 U
b11011001 X
b11011001 [
#48
0Y
b0 !
b0 (
b0 S
0\
b1000 $
b1000 '
b1000 R
b1000 U
b1000 X
b1000 [
#49
b101000 $
b101000 '
b101000 R
b101000 U
b101000 X
b101000 [
#50
1Y
b110 !
b110 (
b110 S
1\
06
0B
0N
1-
b10101100 $
b10101100 '
b10101100 R
b10101100 U
b10101100 X
b10101100 [
b11 #
b11 &
b11 +
b11 .
b11 :
b11 F
b111 "
b111 %
b111 *
#51
1C
b11 W
1O
b11 Z
01
04
17
b11 T
b11 ;
0D
b11 G
0P
12
15
b11011011 )
b11011011 ,
b11011011 Q
b11 /
08
#52
b111 !
b111 (
b111 S
1V
b1101100 $
b1101100 '
b1101100 R
b1101100 U
b1101100 X
b1101100 [
#54
03
0?
0K
b11100100 $
b11100100 '
b11100100 R
b11100100 U
b11100100 X
b11100100 [
b1 #
b1 &
b1 +
b1 .
b1 :
b1 F
#55
0V
0Y
b0 !
b0 (
b0 S
0\
14
b1 T
1@
b1 W
1L
b1 Z
b1 /
05
b1 ;
0A
b1001001 )
b1001001 ,
b1001001 Q
b1 G
0M
b11100110 $
b11100110 '
b11100110 R
b11100110 U
b11100110 X
b11100110 [
#56
1V
1Y
b111 !
b111 (
b111 S
1\
b10110 $
b10110 '
b10110 R
b10110 U
b10110 X
b10110 [
#58
b10010110 $
b10010110 '
b10010110 R
b10010110 U
b10010110 X
b10010110 [
#60
00
0<
0H
b1010011 $
b1010011 '
b1010011 R
b1010011 U
b1010011 X
b1010011 [
b0 #
b0 &
b0 +
b0 .
b0 :
b0 F
#61
11
b0 T
1=
b0 W
1I
b0 Z
b0 /
02
b0 ;
0>
b0 )
b0 ,
b0 Q
b0 G
0J
#62
b11010011 $
b11010011 '
b11010011 R
b11010011 U
b11010011 X
b11010011 [
#63
b11111011 $
b11111011 '
b11111011 R
b11111011 U
b11111011 X
b11111011 [
#64
b101011 $
b101011 '
b101011 R
b101011 U
b101011 X
b101011 [
#66
b10101001 $
b10101001 '
b10101001 R
b10101001 U
b10101001 X
b10101001 [
#68
b1101001 $
b1101001 '
b1101001 R
b1101001 U
b1101001 X
b1101001 [
#70
09
b11001101 $
b11001101 '
b11001101 R
b11001101 U
b11001101 X
b11001101 [
b101 "
b101 %
b101 *
#72
0V
0Y
b0 !
b0 (
b0 S
0\
b10100 $
b10100 '
b10100 R
b10100 U
b10100 X
b10100 [
#74
b10010100 $
b10010100 '
b10010100 R
b10010100 U
b10010100 X
b10010100 [
#75
16
1B
1N
b100 #
b100 &
b100 +
b100 .
b100 :
b100 F
#76
07
b100 T
0O
b100 Z
b100 /
18
b100000100 )
b100000100 ,
b100000100 Q
b100 G
1P
b1010100 $
b1010100 '
b1010100 R
b1010100 U
b1010100 X
b1010100 [
#77
1V
b101 !
b101 (
b101 S
1\
b1110110 $
b1110110 '
b1110110 R
b1110110 U
b1110110 X
b1110110 [
#78
b11110110 $
b11110110 '
b11110110 R
b11110110 U
b11110110 X
b11110110 [
#80
b100010 $
b100010 '
b100010 R
b100010 U
b100010 X
b100010 [
#81
13
1?
1K
b101010 $
b101010 '
b101010 R
b101010 U
b101010 X
b101010 [
b110 #
b110 &
b110 +
b110 .
b110 :
b110 F
#82
04
b110 T
0L
b110 Z
b110 /
15
b110000110 )
b110000110 ,
b110000110 Q
b110 G
1M
b10101010 $
b10101010 '
b10101010 R
b10101010 U
b10101010 X
b10101010 [
#84
b111 !
b111 (
b111 S
1Y
b1001011 $
b1001011 '
b1001011 R
b1001011 U
b1001011 X
b1001011 [
#86
0E
b11001011 $
b11001011 '
b11001011 R
b11001011 U
b11001011 X
b11001011 [
b1 "
b1 %
b1 *
#88
b11001 $
b11001 '
b11001 R
b11001 U
b11001 X
b11001 [
#90
0V
b10 !
b10 (
b10 S
0\
10
1<
1H
b10010101 $
b10010101 '
b10010101 R
b10010101 U
b10010101 X
b10010101 [
b111 #
b111 &
b111 +
b111 .
b111 :
b111 F
#91
b11 !
b11 (
b11 S
1V
01
b111 T
b110000111 )
b110000111 ,
b110000111 Q
b111 /
12
b10110101 $
b10110101 '
b10110101 R
b10110101 U
b10110101 X
b10110101 [
#92
b10 !
b10 (
b10 S
0V
b1110101 $
b1110101 '
b1110101 R
b1110101 U
b1110101 X
b1110101 [
#94
b11 !
b11 (
b11 S
1V
b11110101 $
b11110101 '
b11110101 R
b11110101 U
b11110101 X
b11110101 [
#96
0V
b0 !
b0 (
b0 S
0Y
b100100 $
b100100 '
b100100 R
b100100 U
b100100 X
b100100 [
#98
b1 !
b1 (
b1 S
1V
b10000100 $
b10000100 '
b10000100 R
b10000100 U
b10000100 X
b10000100 [
#99
b101 !
b101 (
b101 S
1\
b10001110 $
b10001110 '
b10001110 R
b10001110 U
b10001110 X
b10001110 [
#100
b100 !
b100 (
b100 S
0V
06
0B
0N
0-
b1001010 $
b1001010 '
b1001010 R
b1001010 U
b1001010 X
b1001010 [
b11 #
b11 &
b11 +
b11 .
b11 :
b11 F
b0 "
b0 %
b0 *
#102
b101 !
b101 (
b101 S
1V
b11001010 $
b11001010 '
b11001010 R
b11001010 U
b11001010 X
b11001010 [
#104
b100 !
b100 (
b100 S
0V
b11010 $
b11010 '
b11010 R
b11010 U
b11010 X
b11010 [
#105
19
b111010 $
b111010 '
b111010 R
b111010 U
b111010 X
b111010 [
b10 "
b10 %
b10 *
#106
b101 !
b101 (
b101 S
1V
0=
0@
b11 W
1>
b110011111 )
b110011111 ,
b110011111 Q
b11 ;
1A
b10111010 $
b10111010 '
b10111010 R
b10111010 U
b10111010 X
b10111010 [
#108
0V
1Y
b10 !
b10 (
b10 S
0\
03
0?
0K
b1110011 $
b1110011 '
b1110011 R
b1110011 U
b1110011 X
b1110011 [
b1 #
b1 &
b1 +
b1 .
b1 :
b1 F
#109
1@
b1 W
b110001111 )
b110001111 ,
b110001111 Q
b1 ;
0A
#110
b11 !
b11 (
b11 S
1V
b11110101 $
b11110101 '
b11110101 R
b11110101 U
b11110101 X
b11110101 [
#112
0V
b0 !
b0 (
b0 S
0Y
b101 $
b101 '
b101 R
b101 U
b101 X
b101 [
#114
b1 !
b1 (
b1 S
1V
b10000101 $
b10000101 '
b10000101 R
b10000101 U
b10000101 X
b10000101 [
#116
b0 !
b0 (
b0 S
0V
b1000101 $
b1000101 '
b1000101 R
b1000101 U
b1000101 X
b1000101 [
#117
b100 !
b100 (
b100 S
1\
b1001101 $
b1001101 '
b1001101 R
b1001101 U
b1001101 X
b1001101 [
#118
b101 !
b101 (
b101 S
1V
b11001101 $
b11001101 '
b11001101 R
b11001101 U
b11001101 X
b11001101 [
#119
b11101101 $
b11101101 '
b11101101 R
b11101101 U
b11101101 X
b11101101 [
#120
0V
b110 !
b110 (
b110 S
1Y
00
0<
0H
b111000 $
b111000 '
b111000 R
b111000 U
b111000 X
b111000 [
b0 #
b0 &
b0 +
b0 .
b0 :
b0 F
#121
b100 !
b100 (
b100 S
0Y
1=
b0 W
b110000111 )
b110000111 ,
b110000111 Q
b0 ;
0>
b111010 $
b111010 '
b111010 R
b111010 U
b111010 X
b111010 [
#122
b101 !
b101 (
b101 S
1V
b10111010 $
b10111010 '
b10111010 R
b10111010 U
b10111010 X
b10111010 [
#124
b100 !
b100 (
b100 S
0V
b1111010 $
b1111010 '
b1111010 R
b1111010 U
b1111010 X
b1111010 [
#125
16
1B
1N
b100 #
b100 &
b100 +
b100 .
b100 :
b100 F
#126
1V
1Y
b11 !
b11 (
b11 S
0\
0C
b100 W
b110100111 )
b110100111 ,
b110100111 Q
b100 ;
1D
b11010010 $
b11010010 '
b11010010 R
b11010010 U
b11010010 X
b11010010 [
#128
b10 !
b10 (
b10 S
0V
b10 $
b10 '
b10 R
b10 U
b10 X
b10 [
#129
1E
b110 "
b110 %
b110 *
#130
1V
b111 !
b111 (
b111 S
1\
1L
b100 Z
b100100111 )
b100100111 ,
b100100111 Q
b100 G
0M
b10000110 $
b10000110 '
b10000110 R
b10000110 U
b10000110 X
b10000110 [
#132
0V
0Y
b0 !
b0 (
b0 S
0\
b1000101 $
b1000101 '
b1000101 R
b1000101 U
b1000101 X
b1000101 [
#133
b1100101 $
b1100101 '
b1100101 R
b1100101 U
b1100101 X
b1100101 [
#134
b1 !
b1 (
b1 S
1V
b11100101 $
b11100101 '
b11100101 R
b11100101 U
b11100101 X
b11100101 [
#135
13
1?
1K
b11101101 $
b11101101 '
b11101101 R
b11101101 U
b11101101 X
b11101101 [
b110 #
b110 &
b110 +
b110 .
b110 :
b110 F
#136
0V
1Y
b110 !
b110 (
b110 S
1\
0@
b110 W
0L
b110 Z
b110 ;
1A
b110110111 )
b110110111 ,
b110110111 Q
b110 G
1M
b111101 $
b111101 '
b111101 R
b111101 U
b111101 X
b111101 [
#138
b111 !
b111 (
b111 S
1V
b10111101 $
b10111101 '
b10111101 R
b10111101 U
b10111101 X
b10111101 [
#140
b110 !
b110 (
b110 S
0V
09
b1011001 $
b1011001 '
b1011001 R
b1011001 U
b1011001 X
b1011001 [
b100 "
b100 %
b100 *
#142
b111 !
b111 (
b111 S
1V
b11011001 $
b11011001 '
b11011001 R
b11011001 U
b11011001 X
b11011001 [
#143
b11011011 $
b11011011 '
b11011011 R
b11011011 U
b11011011 X
b11011011 [
#144
0V
0Y
b0 !
b0 (
b0 S
0\
b10 $
b10 '
b10 R
b10 U
b10 X
b10 [
#146
b1 !
b1 (
b1 S
1V
b10000010 $
b10000010 '
b10000010 R
b10000010 U
b10000010 X
b10000010 [
#147
b10100010 $
b10100010 '
b10100010 R
b10100010 U
b10100010 X
b10100010 [
#148
b0 !
b0 (
b0 S
0V
b1100010 $
b1100010 '
b1100010 R
b1100010 U
b1100010 X
b1100010 [
#150
b1 !
b1 (
b1 S
1V
06
0B
0N
10
1<
1H
1-
b11100110 $
b11100110 '
b11100110 R
b11100110 U
b11100110 X
b11100110 [
b11 #
b11 &
b11 +
b11 .
b11 :
b11 F
b101 "
b101 %
b101 *
#151
b101 !
b101 (
b101 S
1\
1O
0I
b11 Z
17
b11 T
0P
b11 G
1J
b11110011 )
b11110011 ,
b11110011 Q
b11 /
08
#152
0V
b0 !
b0 (
b0 S
0\
b110110 $
b110110 '
b110110 R
b110110 U
b110110 X
b110110 [
#153
b10 !
b10 (
b10 S
1Y
b111110 $
b111110 '
b111110 R
b111110 U
b111110 X
b111110 [
#154
b10011100 $
b10011100 '
b10011100 R
b10011100 U
b10011100 X
b10011100 [
#156
1V
b111 !
b111 (
b111 S
1\
b1011101 $
b1011101 '
b1011101 R
b1011101 U
b1011101 X
b1011101 [
#158
b11011101 $
b11011101 '
b11011101 R
b11011101 U
b11011101 X
b11011101 [
#160
0V
b10 !
b10 (
b10 S
0\
b1001 $
b1001 '
b1001 R
b1001 U
b1001 X
b1001 [
#161
b101001 $
b101001 '
b101001 R
b101001 U
b101001 X
b101001 [
#162
b0 !
b0 (
b0 S
0Y
03
0?
0K
b10100001 $
b10100001 '
b10100001 R
b10100001 U
b10100001 X
b10100001 [
b1 #
b1 &
b1 +
b1 .
b1 :
b1 F
#163
14
b1 T
1L
b1 Z
b1 /
05
b1110001 )
b1110001 ,
b1110001 Q
b1 G
0M
#164
b1100001 $
b1100001 '
b1100001 R
b1100001 U
b1100001 X
b1100001 [
#165
b1100011 $
b1100011 '
b1100011 R
b1100011 U
b1100011 X
b1100011 [
#166
b11100011 $
b11100011 '
b11100011 R
b11100011 U
b11100011 X
b11100011 [
#168
1V
b101 !
b101 (
b101 S
1\
b10010 $
b10010 '
b10010 R
b10010 U
b10010 X
b10010 [
#170
b10010110 $
b10010110 '
b10010110 R
b10010110 U
b10010110 X
b10010110 [
#171
b111 !
b111 (
b111 S
1Y
b10011110 $
b10011110 '
b10011110 R
b10011110 U
b10011110 X
b10011110 [
#172
0E
b1011110 $
b1011110 '
b1011110 R
b1011110 U
b1011110 X
b1011110 [
b1 "
b1 %
b1 *
#174
b11011110 $
b11011110 '
b11011110 R
b11011110 U
b11011110 X
b11011110 [
#175
16
1B
1N
19
b11111110 $
b11111110 '
b11111110 R
b11111110 U
b11111110 X
b11111110 [
b101 #
b101 &
b101 +
b101 .
b101 :
b101 F
b11 "
b11 %
b11 *
#176
b11 !
b11 (
b11 S
0\
07
b101 T
0=
1@
b101 W
b101 /
18
1>
b1101101 )
b1101101 ,
b1101101 Q
b101 ;
0A
b101100 $
b101100 '
b101100 R
b101100 U
b101100 X
b101100 [
#178
b10101100 $
b10101100 '
b10101100 R
b10101100 U
b10101100 X
b10101100 [
#180
00
0<
0H
b1100001 $
b1100001 '
b1100001 R
b1100001 U
b1100001 X
b1100001 [
b100 #
b100 &
b100 +
b100 .
b100 :
b100 F
#181
0V
b0 !
b0 (
b0 S
0Y
11
b100 T
1=
b100 W
b100 /
02
b1100100 )
b1100100 ,
b1100100 Q
b100 ;
0>
#182
b11000001 $
b11000001 '
b11000001 R
b11000001 U
b11000001 X
b11000001 [
#184
b100 !
b100 (
b100 S
1\
b10001 $
b10001 '
b10001 R
b10001 U
b10001 X
b10001 [
#186
b10010001 $
b10010001 '
b10010001 R
b10010001 U
b10010001 X
b10010001 [
#187
1V
b111 !
b111 (
b111 S
1Y
b10010011 $
b10010011 '
b10010011 R
b10010011 U
b10010011 X
b10010011 [
#188
b1010011 $
b1010011 '
b1010011 R
b1010011 U
b1010011 X
b1010011 [
#189
13
1?
1K
b1111011 $
b1111011 '
b1111011 R
b1111011 U
b1111011 X
b1111011 [
b110 #
b110 &
b110 +
b110 .
b110 :
b110 F
#190
04
b110 T
0@
b110 W
b110 /
15
b1110110 )
b1110110 ,
b1110110 Q
b110 ;
1A
b11111111 $
b11111111 '
b11111111 R
b11111111 U
b11111111 X
b11111111 [
#192
b11 !
b11 (
b11 S
0\
b101110 $
b101110 '
b101110 R
b101110 U
b101110 X
b101110 [
#194
b10101110 $
b10101110 '
b10101110 R
b10101110 U
b10101110 X
b10101110 [
#196
b1001110 $
b1001110 '
b1001110 R
b1001110 U
b1001110 X
b1001110 [
#198
0V
b0 !
b0 (
b0 S
0Y
b11000100 $
b11000100 '
b11000100 R
b11000100 U
b11000100 X
b11000100 [
#200
b100 !
b100 (
b100 S
1\
06
0B
0N
0-
b10000 $
b10000 '
b10000 R
b10000 U
b10000 X
b10000 [
b10 #
b10 &
b10 +
b10 .
b10 :
b10 F
b10 "
b10 %
b10 *
#201
1C
b10 W
b1010110 )
b1010110 ,
b1010110 Q
b10 ;
0D
#202
b10010000 $
b10010000 '
b10010000 R
b10010000 U
b10010000 X
b10010000 [
#203
b10110000 $
b10110000 '
b10110000 R
b10110000 U
b10110000 X
b10110000 [
#204
b1110001 $
b1110001 '
b1110001 R
b1110001 U
b1110001 X
b1110001 [
#206
b11110001 $
b11110001 '
b11110001 R
b11110001 U
b11110001 X
b11110001 [
#207
b101 !
b101 (
b101 S
1V
b11111001 $
b11111001 '
b11111001 R
b11111001 U
b11111001 X
b11111001 [
#208
b1 !
b1 (
b1 S
0\
b101001 $
b101001 '
b101001 R
b101001 U
b101001 X
b101001 [
#209
b101011 $
b101011 '
b101011 R
b101011 U
b101011 X
b101011 [
#210
b11 !
b11 (
b11 S
1Y
10
1<
1H
09
b10001111 $
b10001111 '
b10001111 R
b10001111 U
b10001111 X
b10001111 [
b11 #
b11 &
b11 +
b11 .
b11 :
b11 F
b0 "
b0 %
b0 *
#212
b1001111 $
b1001111 '
b1001111 R
b1001111 U
b1001111 X
b1001111 [
#214
b11001111 $
b11001111 '
b11001111 R
b11001111 U
b11001111 X
b11001111 [
#215
1E
b100 "
b100 %
b100 *
#216
b10 !
b10 (
b10 S
0V
0L
b11 Z
03
0?
0K
b11010110 )
b11010110 ,
b11010110 Q
b11 G
1M
b10110 $
b10110 '
b10110 R
b10110 U
b10110 X
b10110 [
b1 #
b1 &
b1 +
b1 .
b1 :
b1 F
#217
b110 !
b110 (
b110 S
1\
1L
b1 Z
b1010110 )
b1010110 ,
b1010110 Q
b1 G
0M
b110110 $
b110110 '
b110110 R
b110110 U
b110110 X
b110110 [
#218
b10110110 $
b10110110 '
b10110110 R
b10110110 U
b10110110 X
b10110110 [
#220
b100 !
b100 (
b100 S
0Y
b1110000 $
b1110000 '
b1110000 R
b1110000 U
b1110000 X
b1110000 [
#222
b11110000 $
b11110000 '
b11110000 R
b11110000 U
b11110000 X
b11110000 [
#224
b0 !
b0 (
b0 S
0\
b0 $
b0 '
b0 R
b0 U
b0 X
b0 [
#225
b1 !
b1 (
b1 S
1V
16
1B
1N
b1000 $
b1000 '
b1000 R
b1000 U
b1000 X
b1000 [
b101 #
b101 &
b101 +
b101 .
b101 :
b101 F
#226
0O
b101 Z
b101010110 )
b101010110 ,
b101010110 Q
b101 G
1P
b10001000 $
b10001000 '
b10001000 R
b10001000 U
b10001000 X
b10001000 [
#228
b1001001 $
b1001001 '
b1001001 R
b1001001 U
b1001001 X
b1001001 [
#230
b11 !
b11 (
b11 S
1Y
b11001101 $
b11001101 '
b11001101 R
b11001101 U
b11001101 X
b11001101 [
#231
b111 !
b111 (
b111 S
1\
b11101111 $
b11101111 '
b11101111 R
b11101111 U
b11101111 X
b11101111 [
#232
b111111 $
b111111 '
b111111 R
b111111 U
b111111 X
b111111 [
#234
b110 !
b110 (
b110 S
0V
b10110111 $
b10110111 '
b10110111 R
b10110111 U
b10110111 X
b10110111 [
#236
b1110111 $
b1110111 '
b1110111 R
b1110111 U
b1110111 X
b1110111 [
#238
b10 !
b10 (
b10 S
0\
b11010111 $
b11010111 '
b11010111 R
b11010111 U
b11010111 X
b11010111 [
#240
b0 !
b0 (
b0 S
0Y
00
0<
0H
b10 $
b10 '
b10 R
b10 U
b10 X
b10 [
b100 #
b100 &
b100 +
b100 .
b100 :
b100 F
#241
b100 !
b100 (
b100 S
1\
1I
b100 Z
b100010110 )
b100010110 ,
b100010110 Q
b100 G
0J
#242
b0 !
b0 (
b0 S
0\
b10000000 $
b10000000 '
b10000000 R
b10000000 U
b10000000 X
b10000000 [
#243
b1 !
b1 (
b1 S
1V
13
1?
1K
b10001000 $
b10001000 '
b10001000 R
b10001000 U
b10001000 X
b10001000 [
b110 #
b110 &
b110 +
b110 .
b110 :
b110 F
#244
b101 !
b101 (
b101 S
1\
0L
b110 Z
b110010110 )
b110010110 ,
b110010110 Q
b110 G
1M
b1001000 $
b1001000 '
b1001000 R
b1001000 U
b1001000 X
b1001000 [
#245
19
b1101000 $
b1101000 '
b1101000 R
b1101000 U
b1101000 X
b1101000 [
b110 "
b110 %
b110 *
