or2/or2.v
`timescale 1ns/1ns
module or2(a,b,out);
    input a,b;
    output out;
    assign out = a | b;
endmodule

basic_modules/or2/or2_test.v
`include "or2.v"
`timescale 1ns/1ns

module or2_test;
    reg a, b;
    wire out;
    initial begin
        a <= 0;
        b <= 0;
    end
    or2 dd0(.a(a),.b(b),.out(out));
    always #10 a = ~a;
    always #5 b = ~b;
    initial begin
        $dumpfile("or2_test.vcd");
        $dumpvars;
        $display("test complete");
        #50;
        $finish;
    end
endmodule

basic_modules/or2/or2_test.vcd
$date
	Mon May 23 00:05:35 2022
$end
$version
	Icarus Verilog
$end
$timescale
	1ns
$end
$scope module or2_test $end
$var wire 1 ! out $end
$var reg 1 " a $end
$var reg 1 # b $end
$scope module dd0 $end
$var wire 1 " a $end
$var wire 1 # b $end
$var wire 1 ! out $end
$upscope $end
$upscope $end
$enddefinitions $end
#0
$dumpvars
0#
0"
0!
$end
#5
1!
1#
#10
0#
1"
#15
1#
#20
0!
0#
0"
#25
1!
1#
#30
0#
1"
#35
1#
#40
0!
0#
0"
#45
1!
1#
#50
0#
1"
