nor2/nor2.v
`timescale 1ns/1ns
module nor2(a,b,out);
    input a,b;
    output out;
    assign out = ~(a | b);
endmodule

nor2/nor2_test.v
`include "nor2.v"
`timescale 1ns/1ns

module nor2_test;
    reg a, b;
    wire out;
    initial begin
        a <= 0;
        b <= 0;
    end
    nor2 dd0(.a(a),.b(b),.out(out));
    always #10 a = ~a;
    always #5 b = ~b;
    initial begin
        $dumpfile("nor2_test.vcd");
        $dumpvars;
        $display("test complete");
        #50;
        $finish;
    end
endmodule

nor2/nor2_test.vcd
$date
	Sun May 22 23:54:54 2022
$end
$version
	Icarus Verilog
$end
$timescale
	1ns
$end
$scope module nor2_test $end
$var wire 1 ! out $end
$var reg 1 " a $end
$var reg 1 # b $end
$scope module dd0 $end
$var wire 1 " a $end
$var wire 1 # b $end
$var wire 1 ! out $end
$upscope $end
$upscope $end
$enddefinitions $end
#0
$dumpvars
0#
0"
1!
$end
#5
0!
1#
#10
0#
1"
#15
1#
#20
1!
0#
0"
#25
0!
1#
#30
0#
1"
#35
1#
#40
1!
0#
0"
#45
0!
1#
#50
0#
1"
